KolejkaForeman-0.1.202310121859-nspkg.pth
kolejka/foreman/__init__.py
kolejka/foreman/__nonpath__.py
kolejka/foreman/foreman.py
KolejkaForeman-0.1.202310121859.dist-info/METADATA
KolejkaForeman-0.1.202310121859.dist-info/WHEEL
KolejkaForeman-0.1.202310121859.dist-info/entry_points.txt
KolejkaForeman-0.1.202310121859.dist-info/namespace_packages.txt
KolejkaForeman-0.1.202310121859.dist-info/top_level.txt
KolejkaForeman-0.1.202310121859.dist-info/RECORD
