Metadata-Version: 2.1
Name: KolejkaForeman
Version: 0.1.202310121859
Summary: Kolejka Foreman
Home-page: https://github.com/kolejka/kolejka
Author: KOLEJKA
Author-email: kolejka@matinf.uj.edu.pl
License: MIT
Platform: UNKNOWN
Requires-Python: >=3.7
Requires-Dist: KolejkaClient
Requires-Dist: KolejkaCommon
Requires-Dist: KolejkaWorker
Requires-Dist: setproctitle
